PyReprism/__init__.py
PyReprism/languages/__init__.py
PyReprism/languages/abap.py
PyReprism/languages/actionscript.py
PyReprism/languages/ada.py
PyReprism/languages/apacheconf.py
PyReprism/languages/apl.py
PyReprism/languages/applescript.py
PyReprism/languages/arduino.py
PyReprism/languages/arff.py
PyReprism/languages/asciidoc.py
PyReprism/languages/asm6502.py
PyReprism/languages/aspnet.py
PyReprism/languages/autohotkey.py
PyReprism/languages/autoit.py
PyReprism/languages/bash.py
PyReprism/languages/basic.py
PyReprism/languages/batch.py
PyReprism/languages/bison.py
PyReprism/languages/brainfuck.py
PyReprism/languages/bro.py
PyReprism/languages/c.py
PyReprism/languages/clike.py
PyReprism/languages/clojure.py
PyReprism/languages/coffeescript.py
PyReprism/languages/cpp.py
PyReprism/languages/crystal.py
PyReprism/languages/csharp.py
PyReprism/languages/csp.py
PyReprism/languages/css.py
PyReprism/languages/css_extras.py
PyReprism/languages/d.py
PyReprism/languages/dart.py
PyReprism/languages/diff.py
PyReprism/languages/django.py
PyReprism/languages/docker.py
PyReprism/languages/eiffel.py
PyReprism/languages/elixir.py
PyReprism/languages/erb.py
PyReprism/languages/erlang.py
PyReprism/languages/flow.py
PyReprism/languages/fortran.py
PyReprism/languages/fsharp.py
PyReprism/languages/gedcom.py
PyReprism/languages/gherkin.py
PyReprism/languages/git.py
PyReprism/languages/glsl.py
PyReprism/languages/go.py
PyReprism/languages/graphql.py
PyReprism/languages/groovy.py
PyReprism/languages/haml.py
PyReprism/languages/handlebars.py
PyReprism/languages/haskell.py
PyReprism/languages/haxe.py
PyReprism/languages/hpkp.py
PyReprism/languages/hsts.py
PyReprism/languages/html.py
PyReprism/languages/ichigojam.py
PyReprism/languages/icon.py
PyReprism/languages/inform7.py
PyReprism/languages/ini.py
PyReprism/languages/io.py
PyReprism/languages/j.py
PyReprism/languages/java.py
PyReprism/languages/javascript.py
PyReprism/languages/jolie.py
PyReprism/languages/json.py
PyReprism/languages/jsx.py
pyreprism-0.0.4.dist-info/METADATA
pyreprism-0.0.4.dist-info/WHEEL
pyreprism-0.0.4.dist-info/licenses/LICENSE
pyreprism-0.0.4.dist-info/RECORD
