Metadata-Version: 2.3
Name: PyReprism
Version: 0.0.4
Summary: Framework for Source Code Preprocessing
Project-URL: Homepage, https://github.com/unlv-evol/PyReprism
Project-URL: Documentation, https://pyreprism.readthedocs.io
Project-URL: Issues, https://github.com/unlv-evol/PyReprism/issues
Author-email: UNLV EVOL LAB <ogenrwot@unlv.nevada.edu>
License: MIT License
License-File: LICENSE
Classifier: Development Status :: 5 - Production/Stable
Classifier: Environment :: Console
Classifier: Intended Audience :: Developers
Classifier: Intended Audience :: Science/Research
Classifier: License :: OSI Approved :: MIT License
Classifier: Operating System :: OS Independent
Classifier: Programming Language :: Python :: 3
Classifier: Programming Language :: Python :: 3.12
Requires-Python: >=3.6
Provides-Extra: dev
Requires-Dist: flake8; extra == 'dev'
Requires-Dist: pytest; extra == 'dev'
Requires-Dist: pytest-cov; extra == 'dev'
